chempy/__init__.py
chempy/_eqsys.py
chempy/_equilibrium.py
chempy/_release.py
chempy/_solution.py
chempy/_url.py
chempy/_util.py
chempy/arrhenius.py
chempy/chemistry.py
chempy/debye_huckel.py
chempy/einstein_smoluchowski.py
chempy/electrolytes.py
chempy/equilibria.py
chempy/eyring.py
chempy/henry.py
chempy/reactionsystem.py
chempy/symbolic.py
chempy/units.py
chempy/electrochemistry/__init__.py
chempy/electrochemistry/nernst.py
chempy/electrochemistry/tests/__init__.py
chempy/electrochemistry/tests/test_nernst.py
chempy/kinetics/__init__.py
chempy/kinetics/_native.py
chempy/kinetics/_rates.py
chempy/kinetics/analysis.py
chempy/kinetics/arrhenius.py
chempy/kinetics/eyring.py
chempy/kinetics/integrated.py
chempy/kinetics/ode.py
chempy/kinetics/rates.py
chempy/kinetics/tests/__init__.py
chempy/kinetics/tests/_derive_analytic_cstr_bireac.ipynb
chempy/kinetics/tests/test__native.py
chempy/kinetics/tests/test__rates.py
chempy/kinetics/tests/test_arrhenius.py
chempy/kinetics/tests/test_eyring.py
chempy/kinetics/tests/test_integrated.py
chempy/kinetics/tests/test_ode.py
chempy/kinetics/tests/test_rates.py
chempy/printing/__init__.py
chempy/printing/js.py
chempy/printing/numbers.py
chempy/printing/pretty.py
chempy/printing/printer.py
chempy/printing/string.py
chempy/printing/table.py
chempy/printing/tables.py
chempy/printing/tex.py
chempy/printing/web.py
chempy/printing/tests/__init__.py
chempy/printing/tests/test_numbers.py
chempy/printing/tests/test_str.py
chempy/printing/tests/test_table.py
chempy/properties/__init__.py
chempy/properties/debye_huckel_radii.py
chempy/properties/gas_sol_electrolytes_schumpe_1993.py
chempy/properties/sulfuric_acid_density_myhre_1998.py
chempy/properties/water_density_tanaka_2001.py
chempy/properties/water_diffusivity_holz_2000.py
chempy/properties/water_permittivity_bradley_pitzer_1979.py
chempy/properties/water_viscosity_korson_1969.py
chempy/properties/tests/__init__.py
chempy/properties/tests/test_gas_sol_electrolytes_schumpe_1993.py
chempy-0.10.0.dist-info/licenses/AUTHORS
chempy-0.10.0.dist-info/licenses/LICENSE
chempy-0.10.0.dist-info/METADATA
chempy-0.10.0.dist-info/WHEEL
chempy-0.10.0.dist-info/top_level.txt
chempy-0.10.0.dist-info/RECORD
