Metadata-Version: 2.4
Name: chempy
Version: 0.10.0
Summary: ChemPy is a Python package useful for solving problems in chemistry.
Home-page: https://github.com/bjodah/chempy
Author: Bjoern I. Dahlgren
Author-email: bjodah@gmail.com
License: BSD-2-Clause
Project-URL: Home, https://github.com/bjodah/chempy
Keywords: chemistry,water properties,physical chemistry
Classifier: Development Status :: 4 - Beta
Classifier: Operating System :: OS Independent
Classifier: Topic :: Scientific/Engineering
Classifier: Topic :: Scientific/Engineering :: Chemistry
Classifier: Programming Language :: Python
Requires-Python: >=3.8
License-File: LICENSE
License-File: AUTHORS
Requires-Dist: numpy>1.11.3
Requires-Dist: scipy>=1.0.1
Requires-Dist: matplotlib>=2.2.3
Requires-Dist: sympy!=1.2,>=1.1.1
Requires-Dist: quantities>=0.12.1
Requires-Dist: pyneqsys>=0.5.7
Requires-Dist: pyodesys>=0.14.5
Requires-Dist: pyparsing>=2.0.3
Requires-Dist: sym>=0.3.7
Requires-Dist: tabulate
Requires-Dist: pulp>=1.6.8
Requires-Dist: dot2tex>=2.11.3
Provides-Extra: integrators
Requires-Dist: pyodeint>=0.10.4; extra == "integrators"
Requires-Dist: pycvodes>=0.14.5; extra == "integrators"
Requires-Dist: pygslodeiv2>=0.9.4; extra == "integrators"
Provides-Extra: solvers
Requires-Dist: pykinsol>=0.1.6; extra == "solvers"
Provides-Extra: native
Requires-Dist: pycompilation>=0.4.12; extra == "native"
Requires-Dist: pycodeexport>=0.1.3; extra == "native"
Requires-Dist: appdirs; extra == "native"
Provides-Extra: docs
Requires-Dist: Sphinx; extra == "docs"
Requires-Dist: sphinx_rtd_theme; extra == "docs"
Requires-Dist: numpydoc; extra == "docs"
Provides-Extra: plotting
Requires-Dist: bokeh>=0.13.0; extra == "plotting"
Requires-Dist: ipywidgets; extra == "plotting"
Provides-Extra: testing
Requires-Dist: black; extra == "testing"
Requires-Dist: pytest>=3.9; extra == "testing"
Requires-Dist: pytest-cov; extra == "testing"
Requires-Dist: pytest-flake8; extra == "testing"
Requires-Dist: rstcheck; extra == "testing"
Provides-Extra: all
Requires-Dist: pyodeint>=0.10.4; extra == "all"
Requires-Dist: pycvodes>=0.14.5; extra == "all"
Requires-Dist: pygslodeiv2>=0.9.4; extra == "all"
Requires-Dist: pykinsol>=0.1.6; extra == "all"
Requires-Dist: pycompilation>=0.4.12; extra == "all"
Requires-Dist: pycodeexport>=0.1.3; extra == "all"
Requires-Dist: appdirs; extra == "all"
Requires-Dist: Sphinx; extra == "all"
Requires-Dist: sphinx_rtd_theme; extra == "all"
Requires-Dist: numpydoc; extra == "all"
Requires-Dist: bokeh>=0.13.0; extra == "all"
Requires-Dist: ipywidgets; extra == "all"
Requires-Dist: black; extra == "all"
Requires-Dist: pytest>=3.9; extra == "all"
Requires-Dist: pytest-cov; extra == "all"
Requires-Dist: pytest-flake8; extra == "all"
Requires-Dist: rstcheck; extra == "all"
Dynamic: author
Dynamic: author-email
Dynamic: classifier
Dynamic: description
Dynamic: home-page
Dynamic: keywords
Dynamic: license-file
Dynamic: provides-extra
Dynamic: requires-dist
Dynamic: requires-python
Dynamic: summary
